codenode/__init__.py
codenode/debug.py
codenode/writer.py
codenode/nodes/__init__.py
codenode/nodes/depth_change.py
codenode/nodes/indentation.py
codenode/nodes/newline.py
codenode_utilities/__init__.py
codenode_utilities/auto_coerce.py
codenode_utilities/joined.py
codenode_utilities/node_transformer.py
codenode_utilities/partitioned_node.py
codenode_utilities/prefixer.py
codenode_utilities/suffixer.py
0xf0f_codenode-1.0.dist-info/LICENSE
0xf0f_codenode-1.0.dist-info/METADATA
0xf0f_codenode-1.0.dist-info/WHEEL
0xf0f_codenode-1.0.dist-info/top_level.txt
0xf0f_codenode-1.0.dist-info/RECORD
