Metadata-Version: 2.1
Name: 0xf0f-codenode
Version: 1.0
Summary: a simple framework for code generation
Home-page: https://github.com/0xf0f/codenode
Author: 0xf0f
Author-email: 0xf0f.dev@gmail.com
License: MIT
Platform: UNKNOWN
Classifier: Programming Language :: Python :: 3
Classifier: License :: OSI Approved :: MIT License
Classifier: Operating System :: OS Independent
Requires-Python: >=3.6
License-File: LICENSE
